{
  "db_name": "PostgreSQL",
  "query": "\n                SELECT o.id, o.slug, o.name, o.logo, o.created_at\n                    FROM organisations o\n                    JOIN organisation_members om\n                    ON o.id = om.organisation_id \n                    WHERE om.user_id = $1\n            ",
  "describe": {
    "columns": [
      {
        "ordinal": 0,
        "name": "id",
        "type_info": "Int8"
      },
      {
        "ordinal": 1,
        "name": "slug",
        "type_info": "Text"
      },
      {
        "ordinal": 2,
        "name": "name",
        "type_info": "Text"
      },
      {
        "ordinal": 3,
        "name": "logo",
        "type_info": "Uuid"
      },
      {
        "ordinal": 4,
        "name": "created_at",
        "type_info": "Timestamptz"
      }
    ],
    "parameters": {
      "Left": [
        "Int8"
      ]
    },
    "nullable": [
      false,
      false,
      false,
      true,
      false
    ]
  },
  "hash": "cf3764a68537f424ba3df068e311fada131159e83fa6bfb0f6a4fc6dd6cf5f00"
}
